LICENSE
MANIFEST.in
README.md
install.json
package.json
pyproject.toml
setup.py
tsconfig.json
additional_resources_menu/__init__.py
additional_resources_menu/_version.py
additional_resources_menu.egg-info/PKG-INFO
additional_resources_menu.egg-info/SOURCES.txt
additional_resources_menu.egg-info/dependency_links.txt
additional_resources_menu.egg-info/not-zip-safe
additional_resources_menu.egg-info/requires.txt
additional_resources_menu.egg-info/top_level.txt
src/index.ts
style/base.css
style/index.css
style/index.js