Metadata-Version: 2.1
Name: additional-resources-menu
Version: 1.0.0
Summary: A JupyterLab extension.
Home-page: https://github.com/github_username/additional_resources_menu
Author: Josh Geden
Author-email: jgeden@lbl.gov
License: BSD-3-Clause
Keywords: Jupyter,JupyterLab,JupyterLab3
Platform: Linux
Platform: Mac OS X
Platform: Windows
Classifier: License :: OSI Approved :: BSD License
Classifier: Programming Language :: Python
Classifier: Programming Language :: Python :: 3
Classifier: Programming Language :: Python :: 3.6
Classifier: Programming Language :: Python :: 3.7
Classifier: Programming Language :: Python :: 3.8
Classifier: Programming Language :: Python :: 3.9
Classifier: Framework :: Jupyter
Requires-Python: >=3.6
